gwasstudio/__init__.py
gwasstudio/cli/__init__.py
gwasstudio/cli/export.py
gwasstudio/cli/info.py
gwasstudio/cli/ingest.py
gwasstudio/cli/list.py
gwasstudio/cli/metadata/__init__.py
gwasstudio/cli/metadata/query.py
gwasstudio/config/__init__.py
gwasstudio/config/config.yaml
gwasstudio/config_manager.py
gwasstudio/dask_client.py
gwasstudio/main.py
gwasstudio/methods/__init__.py
gwasstudio/methods/compute_pheno_variance.py
gwasstudio/methods/dataframe.py
gwasstudio/methods/extraction_methods.py
gwasstudio/methods/locus_breaker.py
gwasstudio/methods/manhattan_plot.py
gwasstudio/methods/meta_analysis.py
gwasstudio/mongo/__init__.py
gwasstudio/mongo/connection_manager.py
gwasstudio/mongo/mixin.py
gwasstudio/mongo/models.py
gwasstudio/utils/__init__.py
gwasstudio/utils/cfg.py
gwasstudio/utils/datatypes.py
gwasstudio/utils/enums.py
gwasstudio/utils/hashing.py
gwasstudio/utils/io.py
gwasstudio/utils/metadata.py
gwasstudio/utils/mongo_manager.py
gwasstudio/utils/path_joiner.py
gwasstudio/utils/s3.py
gwasstudio/utils/snps.py
gwasstudio/utils/tdb_schema.py
gwasstudio/utils/vault.py
gwasstudio-2.13.0.dist-info/METADATA
gwasstudio-2.13.0.dist-info/WHEEL
gwasstudio-2.13.0.dist-info/entry_points.txt
gwasstudio-2.13.0.dist-info/RECORD
