Metadata-Version: 2.3
Name: gwasstudio
Version: 2.13.0
Summary: 
Author: Gianmauro Cuccuru
Author-email: gianmauro.cuccuru@fht.org
Requires-Python: >=3.10,<3.13
Classifier: Programming Language :: Python :: 3
Classifier: Programming Language :: Python :: 3.10
Classifier: Programming Language :: Python :: 3.11
Classifier: Programming Language :: Python :: 3.12
Provides-Extra: plot
Requires-Dist: bokeh (>=3.7.3,<4.0.0)
Requires-Dist: boto3 (>=1.37.11,<2.0.0)
Requires-Dist: botocore (>=1.37.11,<2.0.0)
Requires-Dist: click (>=8.1.8,<9.0.0)
Requires-Dist: cloup (>=3.0.5,<4.0.0)
Requires-Dist: dash-bio (>=1.0.1,<2.0.0) ; extra == "plot"
Requires-Dist: dask (>=2024.12.1,<2025.0.0)
Requires-Dist: dask-gateway (>=2024.1.0,<2025.0.0)
Requires-Dist: dask-jobqueue (>=0.9.0,<0.10.0)
Requires-Dist: hvac (>=2.3.0,<3.0.0)
Requires-Dist: loguru (>=0.7.3,<0.8.0)
Requires-Dist: mongoengine (>=0.29.1,<0.30.0)
Requires-Dist: numpy (>=2.2.1,<2.3.0)
Requires-Dist: pandas (>=2.2.3,<3.0.0)
Requires-Dist: platformdirs (>=4.3.8,<5.0.0)
Requires-Dist: plotly (==6.1.0) ; extra == "plot"
Requires-Dist: polars (>=1.19.0,<2.0.0)
Requires-Dist: pyarrow (>=18.1.0,<19.0.0)
Requires-Dist: ruamel-yaml (>=0.18.10,<0.19.0)
Requires-Dist: scipy (>=1.15.3,<2.0.0)
Requires-Dist: tiledb (>=0.33.2,<0.34.0)
